pqthreads/__init__.py
pqthreads/agents.py
pqthreads/config.py
pqthreads/containers.py
pqthreads/controllers.py
pqthreads/decorator.py
pqthreads/descriptors.py
pqthreads/qt.py
pqthreads/refs.py
pqthreads/utils.py
pqthreads/examples/__init__.py
pqthreads/examples/window.py
pqthreads/examples/worker.py
pqthreads-0.6.1.dist-info/licenses/LICENSE
pqthreads-0.6.1.dist-info/METADATA
pqthreads-0.6.1.dist-info/WHEEL
pqthreads-0.6.1.dist-info/top_level.txt
pqthreads-0.6.1.dist-info/RECORD
