Metadata-Version: 2.4
Name: pqthreads
Version: 0.6.1
Summary: Expose class interfaces from the main GUI Thread in another QThread in Qt for Python
Author-email: Sietze van Buuren <s.van.buuren@gmail.com>
License: Copyright 2024 Sietze van Buuren <s.van.buuren@gmail.com>
Project-URL: Homepage, https://github.com/swvanbuuren/pqthreads
Classifier: Programming Language :: Python :: 3.12
Classifier: License :: OSI Approved :: MIT License
Classifier: Operating System :: OS Independent
Requires-Python: >=3.12
License-File: LICENSE
Requires-Dist: pyside6>=6.10.1
Requires-Dist: wrapt>=2.0.1
Dynamic: license-file
